tika_client/__about__.py
tika_client/__init__.py
tika_client/_base.py
tika_client/_constants.py
tika_client/_resource_meta.py
tika_client/_resource_recursive.py
tika_client/_resource_tika.py
tika_client/client.py
tika_client/data_models.py
tika_client/py.typed
tika_client-0.10.0.dist-info/METADATA
tika_client-0.10.0.dist-info/WHEEL
tika_client-0.10.0.dist-info/licenses/LICENSE.txt
tika_client-0.10.0.dist-info/RECORD
