Metadata-Version: 2.4
Name: tika-client
Version: 0.10.0
Summary: A modern REST client for Apache Tika server
Project-URL: changelog, https://github.com/stumpylog/tika-rest-client/blob/main/CHANGELOG.md
Project-URL: documentation, https://github.com/stumpylog/tika-rest-client#readme
Project-URL: issues, https://github.com/stumpylog/tika-rest-client/issues
Project-URL: source, https://github.com/stumpylog/tika-rest-client
Author-email: Trenton H <rda0128ou@mozmail.com>
License-Expression: MPL-2.0
License-File: LICENSE.txt
Keywords: api,client,html,office,pdf,tika
Classifier: Development Status :: 4 - Beta
Classifier: Environment :: Web Environment
Classifier: Intended Audience :: Developers
Classifier: License :: OSI Approved :: Mozilla Public License 2.0 (MPL 2.0)
Classifier: Operating System :: OS Independent
Classifier: Programming Language :: Python
Classifier: Programming Language :: Python :: 3 :: Only
Classifier: Programming Language :: Python :: 3.9
Classifier: Programming Language :: Python :: 3.10
Classifier: Programming Language :: Python :: 3.11
Classifier: Programming Language :: Python :: 3.12
Classifier: Programming Language :: Python :: 3.13
Classifier: Programming Language :: Python :: Implementation :: CPython
Classifier: Programming Language :: Python :: Implementation :: PyPy
Requires-Python: >=3.9
Requires-Dist: anyio>=4.8
Requires-Dist: httpx>=0.27
Requires-Dist: typing-extensions; python_version < '3.11'
